{
	"all": {
		"changeLogs": {
			"BDFDB": "3.1.7",
			"BetterNsfwTag": "1.3.2",
			"BetterSearchPage": "1.2.3",
			"ChatAliases": "2.4.6",
			"PluginRepo": "2.4.6",
			"StaffTag": "1.5.9"
		},
		"choices": {
			"toastPosition": "right"
		},
		"general": {
			"shareData": true,
			"showToasts": true,
			"showSupportBadges": true,
			"useChromium": false
		},
		"hashes": {
			"0BDFDB.data.json": "5f3dbd0859f9ef1f41a2825a3a14b81b0bca2dd8",
			"0BDFDB.raw.css": "f52cb738c62f9d43592643771b39e0783b93ff1b"
		}
	}
}